pkg_peiwen/__init__.py
pkg_peiwen/function.py
pkg_peiwen-0.1.4.dist-info/METADATA
pkg_peiwen-0.1.4.dist-info/WHEEL
pkg_peiwen-0.1.4.dist-info/top_level.txt
pkg_peiwen-0.1.4.dist-info/RECORD
